tasmotadevicecontroller/__init__.py
tasmotadevicecontroller/tasmota_commands.py
tasmotadevicecontroller/tasmota_types.py
tasmotadevicecontroller-0.0.8.dist-info/LICENSE.md
tasmotadevicecontroller-0.0.8.dist-info/METADATA
tasmotadevicecontroller-0.0.8.dist-info/WHEEL
tasmotadevicecontroller-0.0.8.dist-info/top_level.txt
tasmotadevicecontroller-0.0.8.dist-info/RECORD
