Metadata-Version: 2.1
Name: tasmotadevicecontroller
Version: 0.0.8
Summary: Control Tasmota devices via their web api
Home-page: https://github.com/chaptergy/tasmota-device-controller
Author: chaptergy
License: UNKNOWN
Platform: UNKNOWN
Classifier: Programming Language :: Python :: 3.6
Classifier: License :: OSI Approved :: GNU General Public License v3 (GPLv3)
Classifier: Operating System :: OS Independent
Requires-Python: >=3.6
